{
  "dialogue_id": 3,
  "session_id": 33,
  "total_words": 29,
  "words": [
    "гигаджан",
    "поехали",
    "со",
    "мной",
    "в",
    "армению",
    "с",
    "семьей",
    "знакомиться",
    "будем",
    "я",
    "сама",
    "армянка",
    "че",
    "ты",
    "меня",
    "учишь",
    "вот",
    "ты",
    "тормоз",
    "я",
    "тебя",
    "хотела",
    "познакомить",
    "мда",
    "треш",
    "лучше",
    "не",
    "надо"
  ],
  "unique_words": [
    "познакомить",
    "мной",
    "тормоз",
    "че",
    "хотела",
    "не",
    "вот",
    "мда",
    "я",
    "треш",
    "будем",
    "тебя",
    "лучше",
    "меня",
    "армению",
    "в",
    "надо",
    "гигаджан",
    "учишь",
    "армянка",
    "знакомиться",
    "ты",
    "сама",
    "со",
    "поехали",
    "с",
    "семьей"
  ],
  "unique_count": 27
}