{
  "dialogue_id": 2,
  "session_id": 25,
  "total_words": 34,
  "words": [
    "задолбали",
    "провода",
    "в",
    "этой",
    "квартире",
    "делать",
    "мне",
    "больше",
    "нечего",
    "и",
    "так",
    "забот",
    "хватает",
    "пусть",
    "сами",
    "делают",
    "я",
    "их",
    "ноутбуками",
    "не",
    "пользуюсь",
    "всем",
    "детям",
    "по",
    "ноуту",
    "купили",
    "кроме",
    "лизы",
    "конечно",
    "теперь",
    "ходим",
    "за",
    "провода",
    "запинаемся"
  ],
  "unique_words": [
    "по",
    "купили",
    "мне",
    "кроме",
    "забот",
    "не",
    "конечно",
    "всем",
    "этой",
    "я",
    "делать",
    "провода",
    "пользуюсь",
    "нечего",
    "так",
    "ноуту",
    "ноутбуками",
    "и",
    "теперь",
    "задолбали",
    "больше",
    "в",
    "детям",
    "запинаемся",
    "делают",
    "их",
    "ходим",
    "квартире",
    "лизы",
    "хватает",
    "сами",
    "пусть",
    "за"
  ],
  "unique_count": 33
}